types_aiobotocore_mobile/__init__.py
types_aiobotocore_mobile/__init__.pyi
types_aiobotocore_mobile/__main__.py
types_aiobotocore_mobile/client.py
types_aiobotocore_mobile/client.pyi
types_aiobotocore_mobile/literals.py
types_aiobotocore_mobile/literals.pyi
types_aiobotocore_mobile/paginator.py
types_aiobotocore_mobile/paginator.pyi
types_aiobotocore_mobile/py.typed
types_aiobotocore_mobile/type_defs.py
types_aiobotocore_mobile/type_defs.pyi
types_aiobotocore_mobile/version.py
types_aiobotocore_mobile-2.13.2.dist-info/LICENSE
types_aiobotocore_mobile-2.13.2.dist-info/METADATA
types_aiobotocore_mobile-2.13.2.dist-info/WHEEL
types_aiobotocore_mobile-2.13.2.dist-info/top_level.txt
types_aiobotocore_mobile-2.13.2.dist-info/RECORD
